{
  "entity": [
    {
      "id": 43,
      "name": "snmp",
      "label": "SNMP协议审计",
      "description": "SNMP协议审计，记录SNMP协议通信情况",
      "table_name": "zenvis.t_sta_snmp",
      "data_source": "clickhouse",
      "auto_create": {
        "engine": "MergeTree()",
        "order_by": [
          "uid"
        ],
        "partition_by": "uid"
      }
    }
  ],
  "attribute": [
    {
      "id": 43001,
      "entity": "snmp",
      "name": "uid",
      "label": "会话唯一ID",
      "description": "会话唯一ID",
      "column_name": "uid",
      "column_type": "String",
      "operators": [
        "equal",
        "notequal"
      ],
      "display_selected": true
    },
    {
      "id": 43002,
      "entity": "snmp",
      "name": "ts",
      "label": "时间戳",
      "description": "时间戳",
      "column_name": "ts",
      "column_type": "Int64",
      "operators": [
        "equal",
        "notequal",
        "greatthan",
        "lessthan"
      ],
      "display_selected": true
    },
    {
      "id": 43003,
      "entity": "snmp",
      "name": "src_ip",
      "label": "源IP",
      "description": "源IP",
      "column_name": "src_ip",
      "column_type": "String",
      "operators": [
        "equal",
        "notequal"
      ],
      "display_selected": true
    },
    {
      "id": 43004,
      "entity": "snmp",
      "name": "src_port",
      "label": "源端口",
      "description": "源端口",
      "column_name": "src_port",
      "column_type": "Int32",
      "operators": [
        "equal",
        "notequal",
        "greatthan",
        "lessthan"
      ],
      "display_selected": true
    },
    {
      "id": 43005,
      "entity": "snmp",
      "name": "dst_ip",
      "label": "目的IP",
      "description": "目的IP",
      "column_name": "dst_ip",
      "column_type": "String",
      "operators": [
        "equal",
        "notequal"
      ],
      "display_selected": true
    },
    {
      "id": 43006,
      "entity": "snmp",
      "name": "dst_port",
      "label": "目的端口",
      "description": "目的端口",
      "column_name": "dst_port",
      "column_type": "Int32",
      "operators": [
        "equal",
        "notequal",
        "greatthan",
        "lessthan"
      ],
      "display_selected": true
    },
    {
      "id": 43007,
      "entity": "snmp",
      "name": "logtype",
      "label": "日志类型",
      "description": "日志类型，snmp",
      "column_name": "logtype",
      "column_type": "String",
      "operators": [
        "equal",
        "notequal"
      ],
      "display_selected": true
    },
    {
      "id": 43008,
      "entity": "snmp",
      "name": "devname",
      "label": "设备名称",
      "description": "设备名称",
      "column_name": "devname",
      "column_type": "String",
      "operators": [
        "equal",
        "notequal"
      ],
      "display_selected": true
    },
    {
      "id": 43009,
      "entity": "snmp",
      "name": "ds",
      "label": "年月日",
      "description": "年月日",
      "column_name": "ds",
      "column_type": "String",
      "operators": [
        "equal",
        "notequal"
      ],
      "display_selected": true
    },
    {
      "id": 43010,
      "entity": "snmp",
      "name": "hh",
      "label": "小时",
      "description": "小时",
      "column_name": "hh",
      "column_type": "String",
      "operators": [
        "equal",
        "notequal"
      ],
      "display_selected": true
    },
    {
      "id": 43011,
      "entity": "snmp",
      "name": "vendor",
      "label": "厂商",
      "description": "厂商，sangfor",
      "column_name": "vendor",
      "column_type": "String",
      "operators": [
        "equal",
        "notequal"
      ],
      "display_selected": true
    },
    {
      "id": 43012,
      "entity": "snmp",
      "name": "logid",
      "label": "日志ID",
      "description": "日志ID",
      "column_name": "logid",
      "column_type": "Int64",
      "operators": [
        "equal",
        "notequal",
        "greatthan",
        "lessthan"
      ],
      "display_selected": true
    },
    {
      "id": 43013,
      "entity": "snmp",
      "name": "iptype",
      "label": "IP类型",
      "description": "IP类型，4表示ipv4，6表示ipv6",
      "column_name": "iptype",
      "column_type": "Int32",
      "operators": [
        "equal",
        "notequal",
        "greatthan",
        "lessthan"
      ],
      "display_selected": true
    },
    {
      "id": 43014,
      "entity": "snmp",
      "name": "appproto",
      "label": "应用层协议",
      "description": "应用层协议",
      "column_name": "appproto",
      "column_type": "String",
      "operators": [
        "equal",
        "notequal"
      ],
      "display_selected": true
    },
    {
      "id": 43015,
      "entity": "snmp",
      "name": "transproto",
      "label": "传输层协议",
      "description": "传输层协议",
      "column_name": "transproto",
      "column_type": "String",
      "operators": [
        "equal",
        "notequal"
      ],
      "display_selected": true
    },
    {
      "id": 43016,
      "entity": "snmp",
      "name": "insert_time",
      "label": "创建时间",
      "description": "创建时间",
      "column_name": "insert_time",
      "column_type": "DateTime64(3)",
      "search_type": "date",
      "operators": [
        "greatthan",
        "lessthan",
        "greatequalthan",
        "lessequalthan",
        "between"
      ],
      "display_selected": true
    }
  ]
}